{
  "sections": {
    "75240248-d537-41fc-a2cf-0f6a55fbff7a": {
      "type": "hero-banner-easter",
      "settings": {
        "bg_color": "#f8c6bd",
        "bg_image": "shopify:\/\/shop_images\/curalin_page_desktop-1.png",
        "small_title": "",
        "big_title": "",
        "mobile_alignment": "start",
        "title_color": "",
        "is_title_right": false,
        "is_title_shadow": false,
        "button_title": "",
        "button_link": "",
        "button_link2": "",
        "button_color": "",
        "button_title_color": ""
      }
    },
    "main": {
      "type": "glucose-support",
      "settings": {
        "wht_titl": "What is CuraLin?",
        "wht_desc": "CuraLin is a 100% natural glucose support supplement for people looking to maintain\n                                    healthy blood sugar levels and enjoy life's events to the fullest. It works by\n                                    blending\n                                    ancient Ayurveda practices with modern science and technology into a spectacular,\n                                    synergistic glucose support formula.<br><br>\n\n\n                                    Each CuraLin capsule is manufactured close to the source, using only premium\n                                    ingredients. Secret production processes ensure that each capsule is highly potent\n                                    and\n                                    safe. All facilities are GMP & ISO 9001 certified, independent quality controls\n                                    assures that you get only the safest, highest quality supplements possible. <br><br>\n                                  \n                                    CuraLin comprises of 9 natural ingredients. Scroll down to learn more about the\n                                    formula."
      }
    }
  },
  "order": [
    "75240248-d537-41fc-a2cf-0f6a55fbff7a",
    "main"
  ]
}
